abexp/__init__.py
abexp/core/__init__.py
abexp/core/allocation.py
abexp/core/analysis_bayesian.py
abexp/core/analysis_frequentist.py
abexp/core/design.py
abexp/core/planning.py
abexp/statistics/__init__.py
abexp/statistics/stats_metrics.py
abexp/statistics/stats_tests.py
abexp/visualization/__init__.py
abexp/visualization/analysis_plots.py
abexp-0.0.3.dist-info/AUTHORS.rst
abexp-0.0.3.dist-info/LICENSE
abexp-0.0.3.dist-info/METADATA
abexp-0.0.3.dist-info/WHEEL
abexp-0.0.3.dist-info/top_level.txt
abexp-0.0.3.dist-info/RECORD
