Metadata-Version: 2.1
Name: abexp
Version: 0.0.3
Summary: Python A/B testing experiment library
Home-page: UNKNOWN
Author: 
Author-email: 
License: UNKNOWN
Platform: UNKNOWN
Classifier: Programming Language :: Python :: 3
Classifier: Operating System :: OS Independent
Requires-Python: >=3.8
Requires-Dist: arviz (==0.11.2)
Requires-Dist: lxml (==4.6.3)
Requires-Dist: matplotlib (==3.3.4)
Requires-Dist: numpy (==1.19.5)
Requires-Dist: pandas (==1.1.5)
Requires-Dist: pymc3 (==3.11.2)
Requires-Dist: scikit-learn (==0.24.2)
Requires-Dist: scipy (==1.5.4)
Requires-Dist: statsmodels (==0.12.2)
Requires-Dist: stochatreat (==0.0.8)
Provides-Extra: develop
Requires-Dist: flake8 (==3.9.2) ; extra == 'develop'
Requires-Dist: ipython (==7.23.1) ; extra == 'develop'
Requires-Dist: nbsphinx (==0.8.4) ; extra == 'develop'
Requires-Dist: pandoc (==1.0.2) ; extra == 'develop'
Requires-Dist: pre-commit (==2.12.1) ; extra == 'develop'
Requires-Dist: pytest (==6.2.4) ; extra == 'develop'
Requires-Dist: setuptools (==52.0.0) ; extra == 'develop'
Requires-Dist: sphinx (==4.0.0) ; extra == 'develop'
Requires-Dist: sphinx-rtd-theme (==0.5.2) ; extra == 'develop'
Requires-Dist: wheel (==0.36.2) ; extra == 'develop'
